rpiatipo/Events.py
rpiatipo/EventsTest.py
rpiatipo/__init__.py
rpiatipo-0.0.4.dist-info/METADATA
rpiatipo-0.0.4.dist-info/RECORD
rpiatipo-0.0.4.dist-info/WHEEL
rpiatipo-0.0.4.dist-info/top_level.txt
