Metadata-Version: 2.1
Name: rpiatipo
Version: 0.0.4
Summary: Event system
Home-page: https://gitlab.com/crowdream/rpi-at-ipo
Author: Scott Morse
Author-email: morsescott@hotmail.com
License: UNKNOWN
Platform: UNKNOWN
Classifier: Programming Language :: Python :: 3
Classifier: License :: OSI Approved :: MIT License
Classifier: Operating System :: OS Independent
